brazilian_utils/__init__.py
brazilian_utils-0.1.0.dist-info/METADATA
brazilian_utils-0.1.0.dist-info/RECORD
brazilian_utils-0.1.0.dist-info/WHEEL
brazilian_utils-0.1.0.dist-info/top_level.txt
