Metadata-Version: 2.1
Name: brazilian-utils
Version: 0.1.0
Summary: Utils library for specific Brazilian businesses.
Home-page: https://github.com/brazilian-utils/python
Author: Alex Rocha
Author-email: alex.rochas@yahoo.com.br
License: MIT
Platform: UNKNOWN
